console_retry/__init__.py
console_retry/__main__.py
console_retry/retry.py
console_retry/version.py
console_retry-1.0.4.dist-info/LICENCE
console_retry-1.0.4.dist-info/METADATA
console_retry-1.0.4.dist-info/WHEEL
console_retry-1.0.4.dist-info/entry_points.txt
console_retry-1.0.4.dist-info/top_level.txt
console_retry-1.0.4.dist-info/RECORD
