Metadata-Version: 2.1
Name: console-retry
Version: 1.0.4
Summary: This utility is designed to run any shell command and retry if no new line was written tostdout within a specified timeout
Home-page: https://github.com/NaturalCycles/console-retry
Author: Kristofer Borgström
License: UNKNOWN
Platform: UNKNOWN
Classifier: Programming Language :: Python :: 3.5
Classifier: Programming Language :: Python :: 3.6
Classifier: Programming Language :: Python :: 3.7
Classifier: License :: OSI Approved :: MIT License
Classifier: Operating System :: POSIX :: Linux
Requires-Python: >=3.5
